pypi_zc_tools/__init__.py
pypi_zc_tools/create_excel_data.py
pypi_zc_tools-1.0.1.dist-info/LICENSE
pypi_zc_tools-1.0.1.dist-info/METADATA
pypi_zc_tools-1.0.1.dist-info/WHEEL
pypi_zc_tools-1.0.1.dist-info/entry_points.txt
pypi_zc_tools-1.0.1.dist-info/top_level.txt
pypi_zc_tools-1.0.1.dist-info/RECORD
