Metadata-Version: 2.1
Name: pypi-zc-tools
Version: 1.0.1
Summary: 数据生成工具
Home-page: https://gitee.com/zc_ceshi/pypi_zc_tools
Author: jochen
Author-email: 1099560198@qq.com
License: MIT License
Platform: all
Classifier: Intended Audience :: Developers
Classifier: Operating System :: OS Independent
Classifier: Natural Language :: Chinese (Simplified)
Classifier: Programming Language :: Python
Classifier: Programming Language :: Python :: 3
Classifier: Programming Language :: Python :: 3.6
Classifier: Programming Language :: Python :: 3.7
Classifier: Programming Language :: Python :: 3.8
Classifier: Programming Language :: Python :: 3.9
Classifier: Programming Language :: Python :: 3.10
Classifier: Topic :: Software Development :: Libraries
Classifier: Topic :: Office/Business :: Financial :: Spreadsheet
Classifier: Topic :: Utilities
Requires-Python: >=3.6
License-File: LICENSE
Requires-Dist: click >=8.0.0
Requires-Dist: Faker >=8.0.0
Requires-Dist: openpyxl >=3.0.0
